tmxtagger/__init__.py
tmxtagger/__main__.py
tmxtagger/tmx_batch_tradosizer.py
tmxtagger/tmx_tradosizer.py
tmxtagger-1.0.1.dist-info/LICENSE.txt
tmxtagger-1.0.1.dist-info/METADATA
tmxtagger-1.0.1.dist-info/WHEEL
tmxtagger-1.0.1.dist-info/entry_points.txt
tmxtagger-1.0.1.dist-info/top_level.txt
tmxtagger-1.0.1.dist-info/RECORD
